MANIFEST.in
README.md
setup.cfg
setup.py
versioneer.py
bin/ise-pyshark
bin/ise-pyshark-file
ise_pyshark/__init__.py
ise_pyshark/_version.py
ise_pyshark/apis.py
ise_pyshark/endpointsdb.py
ise_pyshark/eps.py
ise_pyshark/ouidb.py
ise_pyshark/parser.py
ise_pyshark.egg-info/PKG-INFO
ise_pyshark.egg-info/SOURCES.txt
ise_pyshark.egg-info/dependency_links.txt
ise_pyshark.egg-info/requires.txt
ise_pyshark.egg-info/top_level.txt
ise_pyshark/db/androids.json
ise_pyshark/db/apple-os.json
ise_pyshark/db/macoui.db
ise_pyshark/db/macoui.pipe
ise_pyshark/db/macoui.txt
ise_pyshark/db/models.json