Metadata-Version: 2.4
Name: ise_pyshark
Version: 0.8.0
Summary: Custom DPI tool used to passively analyze endpoint data and transmit results via Cisco ISE API messaging for improved endpoint profiling
Home-page: https://github.com/taylor-cook/ise-pyshark
Download-URL: https://github.com/taylor-cook/ise-pyshark
Author: Taylor Cook
Author-email: aacook@cisco.com
License: Apache 2.0; Copyright (c) 2024 Cisco and/or its affiliates.
Keywords: ISE,API,IOT,profiling
Platform: OS X
Platform: Linux
Platform: Windows
Classifier: Development Status :: 4 - Beta
Classifier: Intended Audience :: Developers
Classifier: Natural Language :: English
Classifier: License :: OSI Approved :: Apache Software License
Classifier: Programming Language :: Python :: 3.8
Classifier: Programming Language :: Python :: 3.9
Requires-Python: >=3.8
Requires-Dist: psutil>=5.9.8
Requires-Dist: pyshark>=0.6
Requires-Dist: redis>=5.2.0
Requires-Dist: requests>=2.31.0
Requires-Dist: urllib3>=2.2.2
Requires-Dist: user-agents>=2.2.0
Requires-Dist: versioneer>=0.29
Dynamic: author
Dynamic: author-email
Dynamic: classifier
Dynamic: description
Dynamic: download-url
Dynamic: home-page
Dynamic: keywords
Dynamic: license
Dynamic: platform
Dynamic: requires-dist
Dynamic: requires-python
Dynamic: summary
